{
  "stats": {
    "minecraft:custom": {
      "minecraft:time_since_rest": 2661,
      "minecraft:walk_one_cm": 1802,
      "minecraft:total_world_time": 5025,
      "minecraft:leave_game": 1,
      "minecraft:fly_one_cm": 3422,
      "minecraft:crouch_one_cm": 126,
      "minecraft:sneak_time": 115,
      "minecraft:play_time": 2661,
      "minecraft:jump": 11,
      "minecraft:time_since_death": 2661
    },
    "minecraft:used": {
      "minecraft:grass_block": 10,
      "icbmbasics:monitor": 18,
      "icbmbasics:radar_mk1": 2
    }
  },
  "DataVersion": 4671
}